Metadata-Version: 1.1
Name: fast-coco-eval-python
Version: 0.0.2
Summary: fast coco eval api
Home-page: https://github.com/Mark-ZhouWX/fast-coco-eval
Author: Mark-ZhouWX
Author-email: zhouwuxing@qq.com
License: Apache License 2.0
Platform: UNKNOWN
Classifier: Development Status :: 3 - Alpha
Classifier: Intended Audience :: Developers
Classifier: Programming Language :: Python :: 3
Classifier: Programming Language :: Python :: 3.7
Classifier: Programming Language :: Python :: 3.8
Classifier: Programming Language :: Python :: 3.9
Classifier: Programming Language :: Python :: 3.10
